litegraph/__init__.py
litegraph/__main__.py
litegraph/version.py
litegraph/js/dist/index.html
litegraph/js/dist/assets/index-C644zcUZ.css
litegraph/js/dist/assets/index-Dv-GfcqU.js
litegraph-0.0.2.dist-info/METADATA
litegraph-0.0.2.dist-info/WHEEL
litegraph-0.0.2.dist-info/entry_points.txt
litegraph-0.0.2.dist-info/licenses/LICENSE
litegraph-0.0.2.dist-info/RECORD
