Metadata-Version: 2.4
Name: litegraph
Version: 0.0.2
Summary: A Graph Node Engine
Project-URL: Homepage, https://github.com/jiauzhang/litegraph
Author-email: Jiau Zhang <jiauzhang@163.com>
License-File: LICENSE
Keywords: Artificial Intelligence,Deep Learning
Classifier: Intended Audience :: Developers
Classifier: License :: OSI Approved :: GNU General Public License v3 (GPLv3)
Classifier: Programming Language :: Python :: 3.10
Classifier: Topic :: Scientific/Engineering :: Artificial Intelligence
Requires-Python: >=3.10
Requires-Dist: fastapi>=0.116.0
Requires-Dist: uvicorn
Provides-Extra: dev
Requires-Dist: pytest>=8.3.4; extra == 'dev'
